[
    {
        "company_id": "acme_dynamics",
        "named_insured": "Acme Dynamics LLC",
        "fein": "12-3456789",
        "entity_type": "LLC",
        "state_of_incorporation": "Delaware",
        "address": "1200 Industrial Parkway",
        "city": "Wilmington",
        "state": "DE",
        "zip": "19801",
        "phone": "(302) 555-0142",
        "website": "www.acmedynamics.com",
        "sic_code": "3599",
        "sic_description": "Industrial and Commercial Machinery NEC",
        "years_in_business": 15,
        "date_established": "2011-03-15",
        "nature_of_business": "Manufacturer of precision industrial machinery and automation equipment for aerospace and automotive sectors",
        "annual_revenue": 50000000,
        "total_employees": 250,
        "total_payroll": 18500000,
        "lob": "DO",
        "board_size": 7,
        "independent_directors": 4,
        "board_members": [
            {"name": "Margaret Chen", "title": "Chairman & CEO", "is_independent": false, "committee": null, "shares_owned": "12%"},
            {"name": "Robert Hartley", "title": "CFO", "is_independent": false, "committee": null, "shares_owned": "5%"},
            {"name": "Diana Okafor", "title": "Director", "is_independent": true, "committee": "Audit", "shares_owned": "2%"},
            {"name": "James Liu", "title": "Director", "is_independent": true, "committee": "Audit, Compensation", "shares_owned": "1%"},
            {"name": "Patricia Novak", "title": "Director", "is_independent": true, "committee": "Governance", "shares_owned": "<1%"},
            {"name": "Samuel Torres", "title": "Director", "is_independent": true, "committee": "Compensation", "shares_owned": "<1%"},
            {"name": "William Reeves", "title": "COO", "is_independent": false, "committee": null, "shares_owned": "8%"}
        ],
        "total_assets": 42000000,
        "has_audit_committee": true,
        "audit_committee_financial_expert": true,
        "effective_date": "2026-07-01",
        "expiration_date": "2027-07-01",
        "limits_requested": 5000000,
        "retention_requested": 50000,
        "prior_carrier": "Hartford Financial",
        "prior_premium": 32000,
        "regulatory_investigation": null,
        "going_concern": false,
        "securities_class_action": false,
        "board_changes_recent": false,
        "ipo_planned": false,
        "merger_acquisition": false,
        "bankruptcy_history": false,
        "non_renewed_by_carrier": false,
        "loss_history": [
            {"year": 2023, "claims": 0, "incurred": 0, "paid": 0, "reserves": 0},
            {"year": 2024, "claims": 0, "incurred": 0, "paid": 0, "reserves": 0},
            {"year": 2025, "claims": 0, "incurred": 0, "paid": 0, "reserves": 0}
        ],
        "claim_details": [],
        "financial_data": {
            "current_year": 2025,
            "prior_year": 2024,
            "current_revenue": 50000000,
            "prior_revenue": 47500000,
            "current_net_income": 4200000,
            "prior_net_income": 3800000,
            "current_total_assets": 42000000,
            "prior_total_assets": 39000000,
            "current_total_liabilities": 18000000,
            "prior_total_liabilities": 17000000,
            "current_equity": 24000000,
            "prior_equity": 22000000,
            "auditor_name": "Smith & Associates CPAs",
            "auditor_opinion": "Unqualified"
        },
        "documents_to_generate": ["do_application", "loss_run", "board_resolution"],
        "ground_truth": {
            "classification": "do_application",
            "risk_score": "Green",
            "routing": "assign_to_uw",
            "appetite": "within_appetite",
            "appetite_key_citations": ["§1.2 15 years in business (min 3)", "§2.1 Revenue $50M (range $10M-$500M)", "§3.1 Board 7 members (min 5)", "§3.3 4/7 independent (majority)", "§5.1 0 claims in 5 years (max 2)"],
            "extracted_fields": {
                "named_insured": "Acme Dynamics LLC",
                "annual_revenue": 50000000,
                "board_size": 7,
                "independent_directors": 4,
                "total_employees": 250,
                "state_of_incorporation": "Delaware"
            }
        },
        "data_quality_notes": []
    },
    {
        "company_id": "pinnacle_software",
        "named_insured": "Pinnacle Software Corp",
        "fein": "23-4567890",
        "entity_type": "Corporation",
        "state_of_incorporation": "California",
        "address": "8900 Technology Drive, Suite 400",
        "city": "San Jose",
        "state": "CA",
        "zip": "95134",
        "phone": "(408) 555-0198",
        "sic_code": "7372",
        "sic_description": "Prepackaged Software",
        "years_in_business": 12,
        "date_established": "2014-06-01",
        "nature_of_business": "Enterprise resource planning (ERP) software for mid-market manufacturing companies",
        "annual_revenue": 85000000,
        "total_employees": 420,
        "lob": "DO",
        "board_size": 8,
        "independent_directors": 5,
        "board_members": [
            {"name": "Andrea Sullivan", "title": "CEO & Director", "is_independent": false, "committee": null, "shares_owned": "15%"},
            {"name": "Thomas Brennan", "title": "CTO & Director", "is_independent": false, "committee": null, "shares_owned": "10%"},
            {"name": "Dr. Priya Sharma", "title": "Director", "is_independent": true, "committee": "Audit", "shares_owned": "2%"},
            {"name": "Michael Goldstein", "title": "Director", "is_independent": false, "committee": null, "shares_owned": "7%"},
            {"name": "Laura Martinez", "title": "Director", "is_independent": true, "committee": "Audit, Governance", "shares_owned": "<1%"},
            {"name": "David Okonkwo", "title": "Director", "is_independent": true, "committee": "Compensation", "shares_owned": "<1%"},
            {"name": "Christine Park", "title": "Director", "is_independent": true, "committee": "Governance", "shares_owned": "<1%"},
            {"name": "Richard Yamamoto", "title": "Director", "is_independent": true, "committee": "Compensation", "shares_owned": "<1%"}
        ],
        "total_assets": 68000000,
        "has_audit_committee": true,
        "audit_committee_financial_expert": true,
        "effective_date": "2026-07-01",
        "expiration_date": "2027-07-01",
        "limits_requested": 10000000,
        "retention_requested": 75000,
        "prior_carrier": "Chubb",
        "prior_premium": 55000,
        "loss_history": [
            {"year": 2023, "claims": 0, "incurred": 0, "paid": 0, "reserves": 0},
            {"year": 2024, "claims": 0, "incurred": 0, "paid": 0, "reserves": 0},
            {"year": 2025, "claims": 0, "incurred": 0, "paid": 0, "reserves": 0}
        ],
        "claim_details": [],
        "financial_data": {
            "current_year": 2025, "prior_year": 2024,
            "current_revenue": 85000000, "prior_revenue": 78000000,
            "current_net_income": 8500000, "prior_net_income": 7200000,
            "current_total_assets": 68000000, "prior_total_assets": 61000000,
            "current_total_liabilities": 22000000, "prior_total_liabilities": 20000000,
            "current_equity": 46000000, "prior_equity": 41000000,
            "auditor_name": "Deloitte & Touche LLP",
            "auditor_opinion": "Unqualified"
        },
        "documents_to_generate": ["do_application", "loss_run"],
        "ground_truth": {
            "classification": "do_application",
            "risk_score": "Green",
            "routing": "assign_to_uw",
            "appetite": "within_appetite",
            "appetite_key_citations": ["§2.1 Revenue $85M", "§3.1 Board 8 (min 5)", "§3.3 5/8 independent (majority)", "§5.1 0 claims"],
            "extracted_fields": {"named_insured": "Pinnacle Software Corp", "annual_revenue": 85000000, "board_size": 8}
        },
        "data_quality_notes": []
    },
    {
        "company_id": "westfield_manufacturing",
        "named_insured": "Westfield Manufacturing Inc",
        "fein": "34-5678901",
        "entity_type": "Corporation",
        "state_of_incorporation": "Ohio",
        "address": "500 Main Street",
        "city": "Westfield Center",
        "state": "OH",
        "zip": "44251",
        "phone": "(330) 555-0167",
        "sic_code": "3444",
        "sic_description": "Sheet Metal Work",
        "years_in_business": 28,
        "date_established": "1998-01-10",
        "nature_of_business": "Precision sheet metal fabrication for HVAC, automotive, and construction industries",
        "annual_revenue": 120000000,
        "total_employees": 650,
        "lob": "DO",
        "board_size": 9,
        "independent_directors": 6,
        "board_members": [
            {"name": "Harold Westfield III", "title": "Chairman", "is_independent": false, "committee": null, "shares_owned": "25%"},
            {"name": "Karen Westfield-Adams", "title": "CEO", "is_independent": false, "committee": null, "shares_owned": "15%"},
            {"name": "Gregory Parsons", "title": "CFO & Director", "is_independent": false, "committee": null, "shares_owned": "3%"},
            {"name": "Dr. Barbara Huang", "title": "Director", "is_independent": true, "committee": "Audit", "shares_owned": "<1%"},
            {"name": "Vincent Russo", "title": "Director", "is_independent": true, "committee": "Audit, Governance", "shares_owned": "<1%"},
            {"name": "Janet Olsen", "title": "Director", "is_independent": true, "committee": "Compensation", "shares_owned": "<1%"},
            {"name": "Frederick James", "title": "Director", "is_independent": true, "committee": "Governance", "shares_owned": "<1%"},
            {"name": "Cynthia Morales", "title": "Director", "is_independent": true, "committee": "Compensation", "shares_owned": "<1%"},
            {"name": "Alan Whitmore", "title": "Director", "is_independent": true, "committee": "Audit", "shares_owned": "<1%"}
        ],
        "total_assets": 95000000,
        "has_audit_committee": true,
        "audit_committee_financial_expert": true,
        "effective_date": "2026-07-01",
        "expiration_date": "2027-07-01",
        "limits_requested": 10000000,
        "retention_requested": 100000,
        "prior_carrier": "Zurich",
        "prior_premium": 78000,
        "loss_history": [
            {"year": 2023, "claims": 0, "incurred": 0, "paid": 0, "reserves": 0},
            {"year": 2024, "claims": 1, "incurred": 45000, "paid": 45000, "reserves": 0},
            {"year": 2025, "claims": 0, "incurred": 0, "paid": 0, "reserves": 0}
        ],
        "claim_details": [
            {"number": "CLM-2024-001", "date_of_loss": "2024-04-15", "claimant": "Former VP of Sales", "type": "D&O Wrongful Termination", "description": "Allegation of wrongful termination during restructuring. Settled quickly.", "status": "Closed", "paid": 45000, "reserves": 0}
        ],
        "financial_data": {
            "current_year": 2025, "prior_year": 2024,
            "current_revenue": 120000000, "prior_revenue": 115000000,
            "current_net_income": 9600000, "prior_net_income": 8900000,
            "current_total_assets": 95000000, "prior_total_assets": 90000000,
            "current_total_liabilities": 35000000, "prior_total_liabilities": 33000000,
            "current_equity": 60000000, "prior_equity": 57000000,
            "auditor_name": "PricewaterhouseCoopers LLP",
            "auditor_opinion": "Unqualified"
        },
        "documents_to_generate": ["do_application", "loss_run", "financial_statement", "board_resolution"],
        "ground_truth": {
            "classification": "do_application",
            "risk_score": "Green",
            "routing": "assign_to_uw",
            "appetite": "within_appetite",
            "appetite_key_citations": ["§2.1 Revenue $120M", "§3.1 Board 9 (min 5)", "§5.1 1 claim in 5 years (max 2)", "§5.2 $45K single claim (max $1M)"],
            "extracted_fields": {"named_insured": "Westfield Manufacturing Inc", "annual_revenue": 120000000, "board_size": 9}
        },
        "data_quality_notes": ["One settled D&O claim in 2024 - tests that 1 claim is still within threshold"]
    },
    {
        "company_id": "techflow_industries",
        "named_insured": "TechFlow Industries Inc",
        "fein": "45-6789012",
        "entity_type": "Corporation",
        "state_of_incorporation": "Delaware",
        "address": "2200 Innovation Boulevard",
        "city": "Austin",
        "state": "TX",
        "zip": "78701",
        "phone": "(512) 555-0234",
        "sic_code": "7372",
        "sic_description": "Prepackaged Software",
        "years_in_business": 8,
        "date_established": "2018-02-14",
        "nature_of_business": "Enterprise cybersecurity software and managed detection services",
        "annual_revenue": 120000000,
        "total_employees": 800,
        "lob": "DO",
        "board_size": 9,
        "independent_directors": 5,
        "board_members": [
            {"name": "Viktor Petrov", "title": "CEO & Chairman", "is_independent": false, "committee": null, "shares_owned": "18%"},
            {"name": "Sarah Kim", "title": "CTO & Director", "is_independent": false, "committee": null, "shares_owned": "12%"},
            {"name": "Daniel Wright", "title": "CFO", "is_independent": false, "committee": null, "shares_owned": "5%"},
            {"name": "Marcus Johnson", "title": "Director (new)", "is_independent": false, "committee": null, "shares_owned": "3%"},
            {"name": "Dr. Elena Vasquez", "title": "Director", "is_independent": true, "committee": "Audit", "shares_owned": "<1%"},
            {"name": "Robert Nakamura", "title": "Director", "is_independent": true, "committee": "Audit", "shares_owned": "<1%"},
            {"name": "Theresa O'Brien", "title": "Director", "is_independent": true, "committee": "Compensation", "shares_owned": "<1%"},
            {"name": "William Abernathy", "title": "Director", "is_independent": true, "committee": "Governance", "shares_owned": "<1%"},
            {"name": "Amara Diallo", "title": "Director", "is_independent": true, "committee": "Governance", "shares_owned": "<1%"}
        ],
        "total_assets": 88000000,
        "has_audit_committee": true,
        "audit_committee_financial_expert": true,
        "regulatory_investigation": "SEC routine inquiry regarding revenue recognition practices (Comment Letter dated June 2025). Company responded; no enforcement action.",
        "regulatory_type": "routine_inquiry",
        "board_changes_recent": true,
        "effective_date": "2026-07-01",
        "expiration_date": "2027-07-01",
        "limits_requested": 10000000,
        "retention_requested": 100000,
        "prior_carrier": "AIG",
        "prior_premium": 85000,
        "loss_history": [
            {"year": 2023, "claims": 1, "incurred": 75000, "paid": 75000, "reserves": 0},
            {"year": 2024, "claims": 0, "incurred": 0, "paid": 0, "reserves": 0},
            {"year": 2025, "claims": 1, "incurred": 150000, "paid": 0, "reserves": 150000, "status": "Open"}
        ],
        "claim_details": [
            {"number": "CLM-2023-001", "date_of_loss": "2023-08-20", "claimant": "Former Board Member", "type": "D&O Breach of Fiduciary Duty", "description": "Allegation of inadequate oversight of executive compensation. Settled.", "status": "Closed", "paid": 75000, "reserves": 0},
            {"number": "CLM-2025-001", "date_of_loss": "2025-03-10", "claimant": "Shareholder Group", "type": "D&O Securities Claim", "description": "Shareholder derivative action alleging misleading revenue projections. Currently in discovery.", "status": "Open", "paid": 0, "reserves": 150000}
        ],
        "financial_data": {
            "current_year": 2025, "prior_year": 2024,
            "current_revenue": 120000000, "prior_revenue": 105000000,
            "current_net_income": 6000000, "prior_net_income": 8500000,
            "current_total_assets": 88000000, "prior_total_assets": 82000000,
            "current_total_liabilities": 38000000, "prior_total_liabilities": 32000000,
            "current_equity": 50000000, "prior_equity": 50000000,
            "auditor_name": "Ernst & Young LLP",
            "auditor_opinion": "Unqualified"
        },
        "documents_to_generate": ["do_application", "loss_run", "financial_statement"],
        "ground_truth": {
            "classification": "do_application",
            "risk_score": "Amber",
            "routing": "assign_to_senior_uw",
            "appetite": "borderline",
            "appetite_key_citations": ["§3.2 SEC routine inquiry - acceptable per guidelines but requires documentation", "§5.1 2 claims in 5 years (at maximum threshold)", "Board turnover - 3 directors replaced in 12 months"],
            "extracted_fields": {"named_insured": "TechFlow Industries Inc", "annual_revenue": 120000000, "board_size": 9, "regulatory_investigation_history": "SEC routine inquiry"}
        },
        "data_quality_notes": ["Tests the critical 'routine SEC inquiry vs enforcement' distinction in §3.2", "Board changes trigger additional scrutiny", "2 claims at the 5-year maximum threshold"]
    },
    {
        "company_id": "horizon_capital",
        "named_insured": "Horizon Capital Group LLC",
        "fein": "56-7890123",
        "entity_type": "LLC",
        "state_of_incorporation": "New York",
        "address": "350 Park Avenue, 22nd Floor",
        "city": "New York",
        "state": "NY",
        "zip": "10022",
        "phone": "(212) 555-0321",
        "sic_code": "6282",
        "sic_description": "Investment Advice",
        "years_in_business": 10,
        "date_established": "2016-09-01",
        "nature_of_business": "Registered investment advisory firm specializing in alternative investments for institutional clients",
        "annual_revenue": 45000000,
        "total_employees": 85,
        "lob": "DO",
        "board_size": 6,
        "independent_directors": 3,
        "board_members": [
            {"name": "Jonathan Blackwell", "title": "Managing Partner & CEO", "is_independent": false, "committee": null, "shares_owned": "30%"},
            {"name": "Rebecca Stein", "title": "Partner & CIO", "is_independent": false, "committee": null, "shares_owned": "20%"},
            {"name": "Christopher Dunn", "title": "Partner & CFO", "is_independent": false, "committee": null, "shares_owned": "15%"},
            {"name": "Dr. Fatima Al-Rashid", "title": "Director", "is_independent": true, "committee": "Audit", "shares_owned": null},
            {"name": "George Lindholm", "title": "Director", "is_independent": true, "committee": "Compliance", "shares_owned": null},
            {"name": "Patricia Cheng", "title": "Director", "is_independent": true, "committee": "Compensation", "shares_owned": null}
        ],
        "total_assets": 32000000,
        "has_audit_committee": true,
        "audit_committee_financial_expert": true,
        "effective_date": "2026-07-01",
        "expiration_date": "2027-07-01",
        "limits_requested": 5000000,
        "retention_requested": 50000,
        "prior_carrier": "Travelers",
        "prior_premium": 42000,
        "loss_history": [
            {"year": 2023, "claims": 0, "incurred": 0, "paid": 0, "reserves": 0},
            {"year": 2024, "claims": 1, "incurred": 85000, "paid": 60000, "reserves": 25000, "status": "Open"},
            {"year": 2025, "claims": 0, "incurred": 0, "paid": 0, "reserves": 0}
        ],
        "claim_details": [
            {"number": "CLM-2024-001", "date_of_loss": "2024-11-05", "claimant": "Investor Group", "type": "D&O Misrepresentation", "description": "Allegation of inadequate risk disclosure in fund offering documents. In mediation.", "status": "Open", "paid": 60000, "reserves": 25000}
        ],
        "financial_data": {
            "current_year": 2025, "prior_year": 2024,
            "current_revenue": 45000000, "prior_revenue": 42000000,
            "current_net_income": 5400000, "prior_net_income": 4800000,
            "current_total_assets": 32000000, "prior_total_assets": 29000000,
            "current_total_liabilities": 10000000, "prior_total_liabilities": 9000000,
            "current_equity": 22000000, "prior_equity": 20000000,
            "auditor_name": "BDO USA LLP",
            "auditor_opinion": "Unqualified"
        },
        "documents_to_generate": ["do_application", "loss_run"],
        "ground_truth": {
            "classification": "do_application",
            "risk_score": "Amber",
            "routing": "assign_to_senior_uw",
            "appetite": "borderline",
            "appetite_key_citations": ["§3.3 Board 3/6 independent = exactly 50% (NOT majority)", "§4.1 SIC 6282 in financial services range 6000-6199 - REQUIRES SPECIAL APPROVAL", "§5.1 1 claim in 5 years (within threshold)"],
            "extracted_fields": {"named_insured": "Horizon Capital Group LLC", "annual_revenue": 45000000, "board_size": 6, "independent_directors": 3}
        },
        "data_quality_notes": ["Tests §3.3 'majority' interpretation: 3 of 6 is exactly 50%, not a majority", "SIC 6282 falls in the 6000-6199 financial services range requiring special approval per §4.1"]
    },
    {
        "company_id": "sterling_advisory",
        "named_insured": "Sterling Advisory Partners LLC",
        "fein": "67-8901234",
        "entity_type": "LLC",
        "state_of_incorporation": "Illinois",
        "address": "180 North LaSalle Street, Suite 3200",
        "city": "Chicago",
        "state": "IL",
        "zip": "60601",
        "phone": "(312) 555-0456",
        "sic_code": "8742",
        "sic_description": "Management Consulting Services",
        "years_in_business": 7,
        "date_established": "2019-04-01",
        "nature_of_business": "Management consulting and digital transformation advisory for Fortune 500 companies",
        "annual_revenue": 28000000,
        "total_employees": 120,
        "lob": "DO",
        "board_size": 5,
        "independent_directors": 3,
        "board_members": [
            {"name": "Alexander Sterling", "title": "Managing Partner", "is_independent": false, "committee": null, "shares_owned": "40%"},
            {"name": "Olivia Hastings", "title": "Senior Partner & CFO", "is_independent": false, "committee": null, "shares_owned": "20%"},
            {"name": "Dr. Raymond Tso", "title": "Director", "is_independent": true, "committee": "Audit", "shares_owned": null},
            {"name": "Maria Gonzalez-Burke", "title": "Director", "is_independent": true, "committee": "Governance", "shares_owned": null},
            {"name": "Kwame Asante", "title": "Director", "is_independent": true, "committee": "Compensation", "shares_owned": null}
        ],
        "total_assets": 18000000,
        "has_audit_committee": true,
        "audit_committee_financial_expert": true,
        "effective_date": "2026-07-01",
        "expiration_date": "2027-07-01",
        "limits_requested": 3000000,
        "retention_requested": 25000,
        "prior_carrier": "Berkley",
        "prior_premium": 22000,
        "loss_history": [
            {"year": 2021, "claims": 1, "incurred": 180000, "paid": 180000, "reserves": 0},
            {"year": 2022, "claims": 0, "incurred": 0, "paid": 0, "reserves": 0},
            {"year": 2023, "claims": 1, "incurred": 220000, "paid": 150000, "reserves": 70000, "status": "Open"},
            {"year": 2024, "claims": 0, "incurred": 0, "paid": 0, "reserves": 0},
            {"year": 2025, "claims": 0, "incurred": 0, "paid": 0, "reserves": 0}
        ],
        "claim_details": [
            {"number": "CLM-2021-001", "date_of_loss": "2021-06-15", "claimant": "Former Partner", "type": "D&O Breach of Duty", "description": "Allegation of breach of partnership agreement during firm restructuring. Settled.", "status": "Closed", "paid": 180000, "reserves": 0},
            {"number": "CLM-2023-001", "date_of_loss": "2023-09-01", "claimant": "Client Company", "type": "D&O Professional Negligence", "description": "Client alleges faulty strategic advice led to failed acquisition. Ongoing litigation.", "status": "Open", "paid": 150000, "reserves": 70000}
        ],
        "financial_data": {
            "current_year": 2025, "prior_year": 2024,
            "current_revenue": 28000000, "prior_revenue": 25000000,
            "current_net_income": 2100000, "prior_net_income": 1800000,
            "current_total_assets": 18000000, "prior_total_assets": 16000000,
            "current_total_liabilities": 6000000, "prior_total_liabilities": 5500000,
            "current_equity": 12000000, "prior_equity": 10500000,
            "auditor_name": "Grant Thornton LLP",
            "auditor_opinion": "Unqualified"
        },
        "documents_to_generate": ["do_application", "loss_run"],
        "ground_truth": {
            "classification": "do_application",
            "risk_score": "Amber",
            "routing": "assign_to_senior_uw",
            "appetite": "borderline",
            "appetite_key_citations": ["§5.1 Exactly 2 D&O claims in 5 years (at maximum threshold)", "§5.2 No single claim > $1M (largest is $220K, within limit)", "One claim still open with reserves"],
            "extracted_fields": {"named_insured": "Sterling Advisory Partners LLC", "annual_revenue": 28000000, "board_size": 5}
        },
        "data_quality_notes": ["Tests §5.1 exact boundary: 'Maximum 2 D&O claims in the last 5 years' - is exactly 2 acceptable or a fail?", "One claim still open and in litigation"]
    },
    {
        "company_id": "novatech_holdings",
        "named_insured": "NovaTech Holdings LLC",
        "fein": "78-9012345",
        "entity_type": "LLC",
        "state_of_incorporation": "Nevada",
        "address": "4500 Paradise Road, Suite 100",
        "city": "Las Vegas",
        "state": "NV",
        "zip": "89169",
        "phone": "(702) 555-0589",
        "sic_code": "7371",
        "sic_description": "Computer Services and Data Processing",
        "years_in_business": 4,
        "date_established": "2022-05-01",
        "nature_of_business": "Cloud-based data analytics platform for hospitality and gaming industry",
        "annual_revenue": 9500000,
        "total_employees": 45,
        "lob": "DO",
        "board_size": 4,
        "independent_directors": 2,
        "board_members": [
            {"name": "Derek Lam", "title": "CEO & Founder", "is_independent": false, "committee": null, "shares_owned": "55%"},
            {"name": "Natasha Popov", "title": "CTO & Co-Founder", "is_independent": false, "committee": null, "shares_owned": "25%"},
            {"name": "Alan Winters", "title": "Director", "is_independent": true, "committee": "Audit", "shares_owned": null},
            {"name": "Dr. Samira Patel", "title": "Director", "is_independent": true, "committee": "Compensation", "shares_owned": null}
        ],
        "total_assets": 6500000,
        "has_audit_committee": true,
        "audit_committee_financial_expert": false,
        "effective_date": "2026-07-01",
        "expiration_date": "2027-07-01",
        "limits_requested": 2000000,
        "retention_requested": 25000,
        "prior_carrier": "None",
        "prior_premium": 0,
        "loss_history": [
            {"year": 2023, "claims": 0, "incurred": 0, "paid": 0, "reserves": 0},
            {"year": 2024, "claims": 0, "incurred": 0, "paid": 0, "reserves": 0},
            {"year": 2025, "claims": 0, "incurred": 0, "paid": 0, "reserves": 0}
        ],
        "claim_details": [],
        "documents_to_generate": ["do_application", "loss_run"],
        "ground_truth": {
            "classification": "do_application",
            "risk_score": "Red",
            "routing": "refer_to_management",
            "appetite": "outside_appetite",
            "appetite_key_citations": ["§2.1 Revenue $9.5M BELOW minimum $10M", "§3.1 Board 4 members BELOW minimum 5", "§1.2 4 years in business (above 3 minimum but see waiver clause)"],
            "extracted_fields": {"named_insured": "NovaTech Holdings LLC", "annual_revenue": 9500000, "board_size": 4}
        },
        "data_quality_notes": ["Revenue $9.5M tests the exact $10M boundary in §2.1", "Board of 4 is below the 5-member minimum in §3.1", "Clean loss history but structural disqualifiers"]
    },
    {
        "company_id": "pacific_ventures",
        "named_insured": "Pacific Ventures Group Inc",
        "fein": "89-0123456",
        "entity_type": "Corporation",
        "state_of_incorporation": "Washington",
        "address": "1001 Fourth Avenue, Suite 4400",
        "city": "Seattle",
        "state": "WA",
        "zip": "98154",
        "phone": "(206) 555-0678",
        "sic_code": "6726",
        "sic_description": "Investment Offices",
        "years_in_business": 18,
        "date_established": "2008-03-01",
        "nature_of_business": "Diversified holding company with investments in real estate, technology, and clean energy",
        "annual_revenue": 75000000,
        "total_employees": 180,
        "lob": "DO",
        "board_size": 6,
        "independent_directors": 3,
        "board_members": [
            {"name": "Harrison Pacific", "title": "Chairman & CEO", "is_independent": false, "committee": null, "shares_owned": "35%"},
            {"name": "Lynn Hashimoto", "title": "President & COO", "is_independent": false, "committee": null, "shares_owned": "10%"},
            {"name": "Frank Donovan", "title": "CFO", "is_independent": false, "committee": null, "shares_owned": "5%"},
            {"name": "Dr. Susan Whitfield", "title": "Director", "is_independent": true, "committee": "Audit", "shares_owned": null},
            {"name": "Michael Oduya", "title": "Director", "is_independent": true, "committee": "Governance", "shares_owned": null},
            {"name": "Jennifer Kwan", "title": "Director", "is_independent": true, "committee": "Compensation", "shares_owned": null}
        ],
        "total_assets": 52000000,
        "has_audit_committee": true,
        "audit_committee_financial_expert": true,
        "going_concern": true,
        "effective_date": "2026-07-01",
        "expiration_date": "2027-07-01",
        "limits_requested": 5000000,
        "retention_requested": 75000,
        "prior_carrier": "Markel",
        "prior_premium": 65000,
        "loss_history": [
            {"year": 2023, "claims": 0, "incurred": 0, "paid": 0, "reserves": 0},
            {"year": 2024, "claims": 1, "incurred": 350000, "paid": 100000, "reserves": 250000, "status": "Open"},
            {"year": 2025, "claims": 0, "incurred": 0, "paid": 0, "reserves": 0}
        ],
        "claim_details": [
            {"number": "CLM-2024-001", "date_of_loss": "2024-07-22", "claimant": "Minority Shareholders", "type": "D&O Breach of Duty", "description": "Minority shareholders allege board failed to disclose deteriorating financial condition. In litigation.", "status": "Open", "paid": 100000, "reserves": 250000}
        ],
        "financial_data": {
            "current_year": 2025, "prior_year": 2024,
            "current_revenue": 75000000, "prior_revenue": 82000000,
            "current_net_income": -4500000, "prior_net_income": -2100000,
            "current_total_assets": 52000000, "prior_total_assets": 58000000,
            "current_total_liabilities": 48000000, "prior_total_liabilities": 42000000,
            "current_equity": 4000000, "prior_equity": 16000000,
            "auditor_name": "KPMG LLP",
            "auditor_opinion": "Going Concern",
            "going_concern_note": "The Company has suffered recurring losses from operations, with net losses of $4.5M in 2025 and $2.1M in 2024. The Company's total liabilities exceed 92% of total assets. These conditions raise substantial doubt about the Company's ability to continue as a going concern."
        },
        "documents_to_generate": ["do_application", "loss_run", "financial_statement"],
        "ground_truth": {
            "classification": "do_application",
            "risk_score": "Red",
            "routing": "refer_to_management",
            "appetite": "outside_appetite",
            "appetite_key_citations": ["§2.2 Going concern qualification from auditor - DISQUALIFYING", "§4.3 Entities with going concern opinions excluded", "§2.3 Negative net income both years (fails 2 of 3 positive)", "D/E ratio: 48M/4M = 12:1 (max 3:1 per §2.4)"],
            "extracted_fields": {"named_insured": "Pacific Ventures Group Inc", "annual_revenue": 75000000, "going_concern_opinion": true}
        },
        "data_quality_notes": ["Going concern is a hard disqualifier under §2.2 and §4.3", "Debt-to-equity ratio 12:1 far exceeds §2.4 maximum of 3:1", "Revenue declining year-over-year"]
    },
    {
        "company_id": "continental_services",
        "named_insured": "Continental Services Inc",
        "fein": "90-1234567",
        "entity_type": "Corporation",
        "state_of_incorporation": "Virginia",
        "address": "7900 Tysons One Place, Suite 800",
        "city": "Tysons",
        "state": "VA",
        "zip": "22102",
        "phone": "(703) 555-0789",
        "sic_code": "7389",
        "sic_description": "Services-Misc Business Services",
        "years_in_business": 22,
        "date_established": "2004-01-15",
        "nature_of_business": "Government contracting services including IT modernization, cybersecurity, and cloud migration for federal agencies",
        "annual_revenue": 200000000,
        "total_employees": 1200,
        "lob": "DO",
        "board_size": 11,
        "independent_directors": 7,
        "board_members": [
            {"name": "Gen. (Ret.) Charles Mitchell", "title": "Chairman", "is_independent": false, "committee": null, "shares_owned": "8%"},
            {"name": "Victoria Langford", "title": "CEO", "is_independent": false, "committee": null, "shares_owned": "6%"},
            {"name": "David Krauss", "title": "CFO", "is_independent": false, "committee": null, "shares_owned": "3%"},
            {"name": "Adm. (Ret.) Nancy Chen", "title": "Director", "is_independent": false, "committee": "Governance", "shares_owned": "2%"},
            {"name": "Dr. Yusuf Ibrahim", "title": "Director", "is_independent": true, "committee": "Audit", "shares_owned": "<1%"},
            {"name": "Carol Ann Fletcher", "title": "Director", "is_independent": true, "committee": "Audit", "shares_owned": "<1%"},
            {"name": "Thomas Rearden", "title": "Director", "is_independent": true, "committee": "Compliance", "shares_owned": "<1%"},
            {"name": "Sandra Volkov", "title": "Director", "is_independent": true, "committee": "Compensation", "shares_owned": "<1%"},
            {"name": "Robert Mensah", "title": "Director", "is_independent": true, "committee": "Governance", "shares_owned": "<1%"},
            {"name": "Dr. Lisa Yamada", "title": "Director", "is_independent": true, "committee": "Compensation", "shares_owned": "<1%"},
            {"name": "James Caldwell", "title": "Director", "is_independent": true, "committee": "Audit", "shares_owned": "<1%"}
        ],
        "total_assets": 145000000,
        "has_audit_committee": true,
        "audit_committee_financial_expert": true,
        "regulatory_investigation": "Department of Justice investigation into billing practices on federal IT modernization contracts. Investigation opened September 2025. Outside counsel retained. Company cooperating fully.",
        "regulatory_type": "doj",
        "effective_date": "2026-07-01",
        "expiration_date": "2027-07-01",
        "limits_requested": 15000000,
        "retention_requested": 250000,
        "prior_carrier": "AIG",
        "prior_premium": 125000,
        "loss_history": [
            {"year": 2023, "claims": 0, "incurred": 0, "paid": 0, "reserves": 0},
            {"year": 2024, "claims": 0, "incurred": 0, "paid": 0, "reserves": 0},
            {"year": 2025, "claims": 1, "incurred": 500000, "paid": 0, "reserves": 500000, "status": "Open"}
        ],
        "claim_details": [
            {"number": "CLM-2025-001", "date_of_loss": "2025-09-15", "claimant": "DOJ Civil Division", "type": "D&O Government Investigation", "description": "DOJ opened investigation into potential False Claims Act violations related to billing on federal IT contracts. Company has retained outside counsel and is cooperating.", "status": "Open", "paid": 0, "reserves": 500000}
        ],
        "financial_data": {
            "current_year": 2025, "prior_year": 2024,
            "current_revenue": 200000000, "prior_revenue": 190000000,
            "current_net_income": 12000000, "prior_net_income": 14000000,
            "current_total_assets": 145000000, "prior_total_assets": 140000000,
            "current_total_liabilities": 65000000, "prior_total_liabilities": 60000000,
            "current_equity": 80000000, "prior_equity": 80000000,
            "auditor_name": "Deloitte & Touche LLP",
            "auditor_opinion": "Unqualified"
        },
        "documents_to_generate": ["do_application", "loss_run", "financial_statement"],
        "ground_truth": {
            "classification": "do_application",
            "risk_score": "Red",
            "routing": "refer_to_management",
            "appetite": "outside_appetite",
            "appetite_key_citations": ["§3.2 Active DOJ investigation - NOT a routine inquiry, this is enforcement-level", "Distinguished from TechFlow's SEC routine inquiry: DOJ investigation is disqualifying"],
            "extracted_fields": {"named_insured": "Continental Services Inc", "annual_revenue": 200000000, "regulatory_investigation_history": "DOJ investigation"}
        },
        "data_quality_notes": ["Tests the critical §3.2 distinction: DOJ investigation is NOT routine, unlike TechFlow's SEC comment letter", "Otherwise strong financials and governance - only the investigation disqualifies"]
    },
    {
        "company_id": "brightline_analytics",
        "named_insured": "Brightline Analytics Corp",
        "fein": "01-2345678",
        "entity_type": "Corporation",
        "state_of_incorporation": "Massachusetts",
        "address": "100 Cambridge Park Drive, Suite 500",
        "city": "Cambridge",
        "state": "MA",
        "zip": "02140",
        "phone": "(617) 555-0890",
        "sic_code": "7372",
        "sic_description": "Prepackaged Software",
        "years_in_business": 9,
        "date_established": "2017-08-01",
        "nature_of_business": "AI-powered analytics platform for healthcare outcomes research",
        "annual_revenue": 60000000,
        "annual_revenue_display": "",
        "total_employees": 280,
        "lob": "DO",
        "board_size": 7,
        "independent_directors": 4,
        "board_members": [
            {"name": "Dr. Emily Zhao", "title": "CEO & Co-Founder", "is_independent": false, "committee": null, "shares_owned": "20%"},
            {"name": "Nathan Brooks", "title": "CTO & Co-Founder", "is_independent": false, "committee": null, "shares_owned": "15%"},
            {"name": "Claire DuBois", "title": "CFO", "is_independent": false, "committee": null, "shares_owned": "5%"},
            {"name": "Dr. Raj Krishnamurthy", "title": "Director", "is_independent": true, "committee": "Audit", "shares_owned": null},
            {"name": "Sarah Johanssen", "title": "Director", "is_independent": true, "committee": "Governance", "shares_owned": null},
            {"name": "Marcus Williams", "title": "Director", "is_independent": true, "committee": "Compensation", "shares_owned": null},
            {"name": "Dr. Ana Reyes", "title": "Director", "is_independent": true, "committee": "Audit", "shares_owned": null}
        ],
        "total_assets": 48000000,
        "has_audit_committee": true,
        "audit_committee_financial_expert": true,
        "effective_date": "2026-07-01",
        "expiration_date": "2027-07-01",
        "limits_requested": 5000000,
        "retention_requested": 50000,
        "prior_carrier": "Hartford",
        "prior_premium": 38000,
        "loss_history": [
            {"year": 2023, "claims": 0, "incurred": 0, "paid": 0, "reserves": 0},
            {"year": 2024, "claims": 0, "incurred": 0, "paid": 0, "reserves": 0},
            {"year": 2025, "claims": 0, "incurred": 0, "paid": 0, "reserves": 0}
        ],
        "claim_details": [],
        "financial_data": {
            "current_year": 2025, "prior_year": 2024,
            "current_revenue": 60000000, "prior_revenue": 52000000,
            "current_net_income": 4800000, "prior_net_income": 3500000,
            "current_total_assets": 48000000, "prior_total_assets": 42000000,
            "current_total_liabilities": 15000000, "prior_total_liabilities": 14000000,
            "current_equity": 33000000, "prior_equity": 28000000,
            "auditor_name": "RSM US LLP",
            "auditor_opinion": "Unqualified"
        },
        "documents_to_generate": ["do_application", "loss_run", "financial_statement"],
        "ground_truth": {
            "classification": "do_application",
            "risk_score": "Amber",
            "routing": "assign_to_senior_uw",
            "appetite": "borderline",
            "appetite_key_citations": ["Revenue field blank on D&O form - requires cross-referencing financial statement", "All other criteria would be within appetite if revenue confirmed"],
            "extracted_fields": {"named_insured": "Brightline Analytics Corp", "annual_revenue": null, "board_size": 7}
        },
        "data_quality_notes": ["INTENTIONAL: Revenue field left BLANK on D&O application form (annual_revenue_display set to empty string)", "Revenue IS available in the financial statement ($60M)", "Tests extraction handling of missing fields and cross-document data reconciliation", "Amber because incomplete data requires manual review even though underlying data is clean"]
    },
    {
        "company_id": "meridian_holdings",
        "named_insured": "Meridian Holdings Corp",
        "fein": "11-3456789",
        "entity_type": "Corporation",
        "state_of_incorporation": "Florida",
        "address": "800 Brickell Avenue, Suite 1200",
        "city": "Miami",
        "state": "FL",
        "zip": "33131",
        "phone": "(305) 555-0901",
        "sic_code": "6159",
        "sic_description": "Federal-Sponsored Credit Agencies",
        "years_in_business": 22,
        "date_established": "2004-06-01",
        "nature_of_business": "Mortgage servicing and credit intermediation for community development financial institutions",
        "annual_revenue": 25000000,
        "total_employees": 150,
        "lob": "GL",
        "going_concern": true,
        "manufacturing_operations": false,
        "effective_date": "2026-07-01",
        "expiration_date": "2027-07-01",
        "limits_requested": 2000000,
        "retention_requested": 25000,
        "prior_carrier": "Liberty Mutual",
        "prior_premium": 18000,
        "loss_history": [
            {"year": 2023, "claims": 5, "incurred": 220000, "paid": 180000, "reserves": 40000},
            {"year": 2024, "claims": 4, "incurred": 190000, "paid": 155000, "reserves": 35000},
            {"year": 2025, "claims": 3, "incurred": 190000, "paid": 120000, "reserves": 70000, "status": "Open"}
        ],
        "claim_details": [
            {"number": "CLM-2023-001", "date_of_loss": "2023-02-10", "claimant": "Visitor", "type": "Bodily Injury", "description": "Slip and fall in office lobby. Settled.", "status": "Closed", "paid": 45000, "reserves": 0},
            {"number": "CLM-2025-003", "date_of_loss": "2025-08-20", "claimant": "Contractor", "type": "Property Damage", "description": "Water damage to neighboring tenant during HVAC repair. In dispute.", "status": "Open", "paid": 0, "reserves": 70000}
        ],
        "loss_notes": "Note: Claim CLM-2025-003 is disputed by insured. Contractor alleges pre-existing water damage. Dispute resolution pending.",
        "financial_data": {
            "current_year": 2025, "prior_year": 2024,
            "current_revenue": 25000000, "prior_revenue": 28000000,
            "current_net_income": -1200000, "prior_net_income": -800000,
            "current_total_assets": 18000000, "prior_total_assets": 20000000,
            "current_total_liabilities": 16000000, "prior_total_liabilities": 15000000,
            "current_equity": 2000000, "prior_equity": 5000000,
            "auditor_name": "Marcum LLP",
            "auditor_opinion": "Going Concern",
            "going_concern_note": "The Company has incurred net losses in each of the past two fiscal years and has experienced a significant decline in equity. These factors raise substantial doubt about the Company's ability to continue as a going concern."
        },
        "documents_to_generate": ["gl_application", "loss_run", "financial_statement"],
        "ground_truth": {
            "classification": "gl_application",
            "risk_score": "Red",
            "routing": "refer_to_management",
            "appetite": "outside_appetite",
            "appetite_key_citations": ["§4.1 SIC 6159 in excluded financial services range 6000-6199", "§4.3 Going concern qualification", "§6.1 12 claims in 3 years exceeds maximum 5"],
            "extracted_fields": {"named_insured": "Meridian Holdings Corp", "annual_revenue": 25000000, "sic_code": "6159"}
        },
        "data_quality_notes": ["Multiple disqualifiers: excluded SIC, going concern, excessive claims", "Disputed claim in loss run tests handling of contested claims"]
    },
    {
        "company_id": "atlas_building",
        "named_insured": "Atlas Building Supply Inc",
        "fein": "22-4567890",
        "entity_type": "Corporation",
        "state_of_incorporation": "Georgia",
        "address": "4200 Peachtree Industrial Boulevard",
        "city": "Norcross",
        "state": "GA",
        "zip": "30071",
        "phone": "(770) 555-0112",
        "sic_code": "5211",
        "sic_description": "Lumber and Other Building Materials Dealers-Retail",
        "years_in_business": 15,
        "date_established": "2011-02-01",
        "nature_of_business": "Retail and wholesale distribution of lumber, roofing, siding, and building materials to contractors and homeowners",
        "annual_revenue": 35000000,
        "total_employees": 95,
        "lob": "GL",
        "manufacturing_operations": false,
        "effective_date": "2026-07-01",
        "expiration_date": "2027-07-01",
        "limits_requested": 2000000,
        "retention_requested": 10000,
        "prior_carrier": "CNA",
        "prior_premium": 15000,
        "loss_history": [
            {"year": 2023, "claims": 1, "incurred": 12000, "paid": 12000, "reserves": 0},
            {"year": 2024, "claims": 0, "incurred": 0, "paid": 0, "reserves": 0},
            {"year": 2025, "claims": 1, "incurred": 8500, "paid": 8500, "reserves": 0}
        ],
        "claim_details": [
            {"number": "CLM-2023-001", "date_of_loss": "2023-05-14", "claimant": "Customer", "type": "Bodily Injury", "description": "Customer struck by falling lumber in warehouse. Minor injury. Settled.", "status": "Closed", "paid": 12000, "reserves": 0},
            {"number": "CLM-2025-001", "date_of_loss": "2025-10-02", "claimant": "Delivery Driver", "type": "Property Damage", "description": "Delivery truck damaged client's fence during material delivery. Settled.", "status": "Closed", "paid": 8500, "reserves": 0}
        ],
        "documents_to_generate": ["gl_application", "loss_run"],
        "ground_truth": {
            "classification": "gl_application",
            "risk_score": "Green",
            "routing": "assign_to_uw",
            "appetite": "within_appetite",
            "appetite_key_citations": ["§1.2 15 years in business (min 2)", "§1.3 Revenue $35M (range $5M-$250M)", "§6.1 2 claims in 3 years (max 5)"],
            "extracted_fields": {"named_insured": "Atlas Building Supply Inc", "annual_revenue": 35000000, "sic_code": "5211"}
        },
        "data_quality_notes": []
    },
    {
        "company_id": "cascade_precision",
        "named_insured": "Cascade Precision Manufacturing LLC",
        "fein": "33-5678901",
        "entity_type": "LLC",
        "state_of_incorporation": "Oregon",
        "address": "2800 NW Industrial Way",
        "city": "Portland",
        "state": "OR",
        "zip": "97210",
        "phone": "(503) 555-0223",
        "sic_code": "3462",
        "sic_description": "Iron and Steel Forgings",
        "years_in_business": 20,
        "date_established": "2006-04-15",
        "nature_of_business": "Precision forging and machining of steel components for aerospace, defense, and energy sectors",
        "annual_revenue": 55000000,
        "total_employees": 310,
        "total_payroll": 22000000,
        "lob": "GL",
        "manufacturing_operations": true,
        "products_liability_exposure": "Steel forgings used in aircraft landing gear, turbine components, and pressure vessels. All products tested to ASTM and AMS specifications.",
        "effective_date": "2026-07-01",
        "expiration_date": "2027-07-01",
        "limits_requested": 5000000,
        "retention_requested": 25000,
        "prior_carrier": "Zurich",
        "prior_premium": 42000,
        "loss_history": [
            {"year": 2023, "claims": 1, "incurred": 35000, "paid": 35000, "reserves": 0},
            {"year": 2024, "claims": 0, "incurred": 0, "paid": 0, "reserves": 0},
            {"year": 2025, "claims": 1, "incurred": 22000, "paid": 22000, "reserves": 0}
        ],
        "claim_details": [
            {"number": "CLM-2023-001", "date_of_loss": "2023-07-20", "claimant": "Employee", "type": "Bodily Injury", "description": "Employee burned by hot metal during forging process. Workers comp primary, GL secondary for premises liability.", "status": "Closed", "paid": 35000, "reserves": 0},
            {"number": "CLM-2025-001", "date_of_loss": "2025-04-11", "claimant": "Visitor", "type": "Bodily Injury", "description": "Vendor representative tripped on uneven floor in shipping area.", "status": "Closed", "paid": 22000, "reserves": 0}
        ],
        "documents_to_generate": ["gl_application", "loss_run", "supplemental_gl"],
        "ground_truth": {
            "classification": "gl_application",
            "risk_score": "Green",
            "routing": "assign_to_uw",
            "appetite": "within_appetite",
            "appetite_key_citations": ["§1.3 Revenue $55M (range $5M-$250M)", "§5.1 SIC 3462 in light manufacturing range 3400-3599 - standard rates", "§5.3 Products liability documented", "§6.1 2 claims in 3 years (max 5)"],
            "extracted_fields": {"named_insured": "Cascade Precision Manufacturing LLC", "annual_revenue": 55000000, "sic_code": "3462"}
        },
        "data_quality_notes": ["SIC 3462 is in the 3400-3599 light manufacturing range - tests §5.1 boundary"]
    },
    {
        "company_id": "granite_peak",
        "named_insured": "Granite Peak Construction Co",
        "fein": "44-6789012",
        "entity_type": "Corporation",
        "state_of_incorporation": "Colorado",
        "address": "1600 Broadway, Suite 2200",
        "city": "Denver",
        "state": "CO",
        "zip": "80202",
        "phone": "(303) 555-0334",
        "sic_code": "1542",
        "sic_description": "General Industrial Buildings and Warehouses",
        "years_in_business": 14,
        "date_established": "2012-09-01",
        "nature_of_business": "Commercial construction - industrial warehouses, data centers, and manufacturing facilities",
        "annual_revenue": 40000000,
        "total_employees": 180,
        "total_payroll": 14000000,
        "lob": "GL",
        "manufacturing_operations": false,
        "construction_operations": true,
        "effective_date": "2026-07-01",
        "expiration_date": "2027-07-01",
        "limits_requested": 5000000,
        "retention_requested": 25000,
        "prior_carrier": "Travelers",
        "prior_premium": 55000,
        "loss_history": [
            {"year": 2023, "claims": 2, "incurred": 95000, "paid": 80000, "reserves": 15000},
            {"year": 2024, "claims": 1, "incurred": 42000, "paid": 42000, "reserves": 0},
            {"year": 2025, "claims": 2, "incurred": 120000, "paid": 65000, "reserves": 55000, "status": "Open"}
        ],
        "claim_details": [
            {"number": "CLM-2023-001", "date_of_loss": "2023-03-10", "claimant": "Subcontractor Employee", "type": "Bodily Injury", "description": "Fall from scaffolding at warehouse construction site.", "status": "Closed", "paid": 65000, "reserves": 0},
            {"number": "CLM-2025-002", "date_of_loss": "2025-11-05", "claimant": "Adjacent Property Owner", "type": "Property Damage", "description": "Excavation work caused foundation cracking in adjacent building. Under investigation.", "status": "Open", "paid": 0, "reserves": 55000}
        ],
        "documents_to_generate": ["gl_application", "loss_run", "supplemental_gl"],
        "ground_truth": {
            "classification": "gl_application",
            "risk_score": "Amber",
            "routing": "assign_to_senior_uw",
            "appetite": "borderline",
            "appetite_key_citations": ["§3.3 Construction operations require separate contractor's liability coverage", "§6.1 5 claims in 3 years (at maximum threshold)", "§6.2 Claims frequency not trending up (2,1,2 pattern)"],
            "extracted_fields": {"named_insured": "Granite Peak Construction Co", "annual_revenue": 40000000, "sic_code": "1542"}
        },
        "data_quality_notes": ["Construction SIC triggers §3.3 separate coverage requirement", "5 claims in 3 years is exactly at the §6.1 maximum threshold"]
    },
    {
        "company_id": "lakeshore_food",
        "named_insured": "Lakeshore Food Processing Inc",
        "fein": "55-7890123",
        "entity_type": "Corporation",
        "state_of_incorporation": "Wisconsin",
        "address": "1250 Lakeshore Drive",
        "city": "Milwaukee",
        "state": "WI",
        "zip": "53202",
        "phone": "(414) 555-0445",
        "sic_code": "2099",
        "sic_description": "Food Preparations NEC",
        "years_in_business": 30,
        "date_established": "1996-01-01",
        "nature_of_business": "Specialty food manufacturing - organic sauces, marinades, and prepared foods for retail and food service distribution",
        "annual_revenue": 70000000,
        "total_employees": 450,
        "total_payroll": 19000000,
        "lob": "GL",
        "manufacturing_operations": true,
        "products_liability_exposure": "Prepared food products distributed through retail grocery chains and food service distributors. FDA-regulated facility with HACCP plan.",
        "effective_date": "2026-07-01",
        "expiration_date": "2027-07-01",
        "limits_requested": 5000000,
        "retention_requested": 25000,
        "prior_carrier": "Nationwide",
        "prior_premium": 35000,
        "loss_history": [
            {"year": 2023, "claims": 1, "incurred": 15000, "paid": 15000, "reserves": 0},
            {"year": 2024, "claims": 0, "incurred": 0, "paid": 0, "reserves": 0},
            {"year": 2025, "claims": 0, "incurred": 0, "paid": 0, "reserves": 0}
        ],
        "claim_details": [
            {"number": "CLM-2023-001", "date_of_loss": "2023-11-15", "claimant": "Employee", "type": "Bodily Injury", "description": "Employee slipped on wet production floor. Minor injury treated on-site.", "status": "Closed", "paid": 15000, "reserves": 0}
        ],
        "documents_to_generate": ["gl_application", "loss_run"],
        "ground_truth": {
            "classification": "gl_application",
            "risk_score": "Green",
            "routing": "assign_to_uw",
            "appetite": "within_appetite",
            "appetite_key_citations": ["§1.3 Revenue $70M", "§5.3 Products liability documented with FDA/HACCP", "§6.1 1 claim in 3 years (max 5)", "SIC 2099 not in excluded ranges"],
            "extracted_fields": {"named_insured": "Lakeshore Food Processing Inc", "annual_revenue": 70000000, "sic_code": "2099"}
        },
        "data_quality_notes": []
    },
    {
        "company_id": "ironworks_heavy",
        "named_insured": "Ironworks Heavy Industries Corp",
        "fein": "66-8901234",
        "entity_type": "Corporation",
        "state_of_incorporation": "Pennsylvania",
        "address": "3400 Steel Way",
        "city": "Pittsburgh",
        "state": "PA",
        "zip": "15201",
        "phone": "(412) 555-0556",
        "sic_code": "3312",
        "sic_description": "Steel Works, Blast Furnaces",
        "years_in_business": 45,
        "date_established": "1981-06-01",
        "nature_of_business": "Primary steel production - structural steel beams, plate steel, and specialty alloys for construction and infrastructure",
        "annual_revenue": 90000000,
        "total_employees": 520,
        "total_payroll": 32000000,
        "lob": "GL",
        "manufacturing_operations": true,
        "products_liability_exposure": "Structural steel used in bridges, buildings, and infrastructure. All products certified to AISC and ASTM standards.",
        "hazmat_handling": false,
        "effective_date": "2026-07-01",
        "expiration_date": "2027-07-01",
        "limits_requested": 10000000,
        "retention_requested": 50000,
        "prior_carrier": "Zurich",
        "prior_premium": 85000,
        "loss_history": [
            {"year": 2023, "claims": 2, "incurred": 125000, "paid": 100000, "reserves": 25000},
            {"year": 2024, "claims": 1, "incurred": 45000, "paid": 45000, "reserves": 0},
            {"year": 2025, "claims": 1, "incurred": 80000, "paid": 50000, "reserves": 30000, "status": "Open"}
        ],
        "claim_details": [
            {"number": "CLM-2023-001", "date_of_loss": "2023-01-20", "claimant": "Employee", "type": "Bodily Injury", "description": "Burns from molten steel splash during pouring operation. Significant injury.", "status": "Closed", "paid": 85000, "reserves": 0},
            {"number": "CLM-2025-001", "date_of_loss": "2025-06-30", "claimant": "Delivery Company", "type": "Property Damage", "description": "Steel beam fell from crane during loading, damaging delivery truck. Under negotiation.", "status": "Open", "paid": 50000, "reserves": 30000}
        ],
        "documents_to_generate": ["gl_application", "loss_run", "supplemental_gl"],
        "ground_truth": {
            "classification": "gl_application",
            "risk_score": "Amber",
            "routing": "assign_to_senior_uw",
            "appetite": "borderline",
            "appetite_key_citations": ["§5.2 SIC 3312 in heavy manufacturing range 3300-3399 - REQUIRES SENIOR UW APPROVAL", "§5.3 Products liability documented", "§6.1 4 claims in 3 years (below 5 max but elevated)"],
            "extracted_fields": {"named_insured": "Ironworks Heavy Industries Corp", "annual_revenue": 90000000, "sic_code": "3312"}
        },
        "data_quality_notes": ["SIC 3312 is in heavy manufacturing range 3300-3399 - tests §5.2 boundary between light and heavy", "Senior UW approval required per guidelines"]
    },
    {
        "company_id": "bayview_chemical",
        "named_insured": "Bayview Chemical Corp",
        "fein": "77-9012345",
        "entity_type": "Corporation",
        "state_of_incorporation": "New Jersey",
        "address": "100 Chemical Drive",
        "city": "Newark",
        "state": "NJ",
        "zip": "07105",
        "phone": "(973) 555-0667",
        "sic_code": "2899",
        "sic_description": "Chemicals and Chemical Preparations NEC",
        "years_in_business": 18,
        "date_established": "2008-01-01",
        "nature_of_business": "Specialty chemical manufacturing - industrial cleaning solutions, surface treatments, and corrosion inhibitors",
        "annual_revenue": 30000000,
        "total_employees": 110,
        "total_payroll": 8500000,
        "lob": "GL",
        "manufacturing_operations": true,
        "products_liability_exposure": "Chemical products used in industrial cleaning and metal treatment. MSDS documentation maintained for all products.",
        "hazmat_handling": true,
        "effective_date": "2026-07-01",
        "expiration_date": "2027-07-01",
        "limits_requested": 5000000,
        "retention_requested": 25000,
        "prior_carrier": "CNA",
        "prior_premium": 48000,
        "loss_history": [
            {"year": 2023, "claims": 1, "incurred": 28000, "paid": 28000, "reserves": 0},
            {"year": 2024, "claims": 1, "incurred": 35000, "paid": 35000, "reserves": 0},
            {"year": 2025, "claims": 0, "incurred": 0, "paid": 0, "reserves": 0}
        ],
        "claim_details": [
            {"number": "CLM-2023-001", "date_of_loss": "2023-09-10", "claimant": "Employee", "type": "Bodily Injury", "description": "Chemical burn from cleaning solution splashback. Treated at urgent care.", "status": "Closed", "paid": 28000, "reserves": 0},
            {"number": "CLM-2024-001", "date_of_loss": "2024-03-22", "claimant": "Neighboring Business", "type": "Property Damage", "description": "Chemical fumes from manufacturing triggered evacuation of adjacent office building.", "status": "Closed", "paid": 35000, "reserves": 0}
        ],
        "documents_to_generate": ["gl_application", "loss_run", "supplemental_gl"],
        "ground_truth": {
            "classification": "gl_application",
            "risk_score": "Amber",
            "routing": "assign_to_senior_uw",
            "appetite": "borderline",
            "appetite_key_citations": ["§3.2 Hazardous materials handling requires environmental supplemental", "§6.1 2 claims in 3 years (within 5 max)", "Chemical exposure claims increase severity risk"],
            "extracted_fields": {"named_insured": "Bayview Chemical Corp", "annual_revenue": 30000000, "sic_code": "2899"}
        },
        "data_quality_notes": ["Hazmat handling triggers §3.2 environmental supplemental requirement", "Chemical exposure claims pattern suggests elevated severity"]
    },
    {
        "company_id": "summit_mining",
        "named_insured": "Summit Mining & Resources Inc",
        "fein": "88-0123456",
        "entity_type": "Corporation",
        "state_of_incorporation": "Montana",
        "address": "1500 Mineral Avenue",
        "city": "Billings",
        "state": "MT",
        "zip": "59101",
        "phone": "(406) 555-0778",
        "sic_code": "1040",
        "sic_description": "Gold Mining",
        "years_in_business": 25,
        "date_established": "2001-01-01",
        "nature_of_business": "Gold and silver mining operations with processing facilities in Montana and Nevada",
        "annual_revenue": 150000000,
        "total_employees": 850,
        "total_payroll": 52000000,
        "lob": "GL",
        "manufacturing_operations": false,
        "hazmat_handling": true,
        "effective_date": "2026-07-01",
        "expiration_date": "2027-07-01",
        "limits_requested": 10000000,
        "retention_requested": 100000,
        "prior_carrier": "Markel",
        "prior_premium": 180000,
        "loss_history": [
            {"year": 2023, "claims": 3, "incurred": 450000, "paid": 350000, "reserves": 100000},
            {"year": 2024, "claims": 2, "incurred": 280000, "paid": 200000, "reserves": 80000},
            {"year": 2025, "claims": 2, "incurred": 320000, "paid": 150000, "reserves": 170000, "status": "Open"}
        ],
        "claim_details": [
            {"number": "CLM-2023-001", "date_of_loss": "2023-04-05", "claimant": "Employee", "type": "Bodily Injury", "description": "Underground rock fall causing crush injury. Significant medical treatment.", "status": "Closed", "paid": 250000, "reserves": 0},
            {"number": "CLM-2025-002", "date_of_loss": "2025-08-15", "claimant": "Environmental Agency", "type": "Environmental", "description": "Tailings pond leak contaminated creek. EPA cleanup order issued.", "status": "Open", "paid": 0, "reserves": 170000}
        ],
        "documents_to_generate": ["gl_application", "loss_run"],
        "ground_truth": {
            "classification": "gl_application",
            "risk_score": "Red",
            "routing": "refer_to_management",
            "appetite": "outside_appetite",
            "appetite_key_citations": ["§4.2 SIC 1040 in mining range 1000-1499 - EXCLUDED", "§6.1 7 claims in 3 years exceeds maximum 5"],
            "extracted_fields": {"named_insured": "Summit Mining & Resources Inc", "annual_revenue": 150000000, "sic_code": "1040"}
        },
        "data_quality_notes": ["SIC 1040 gold mining is in the excluded 1000-1499 range per §4.2", "Environmental claims add complexity"]
    },
    {
        "company_id": "clearwater_environmental",
        "named_insured": "Clearwater Environmental Services LLC",
        "fein": "99-1234567",
        "entity_type": "LLC",
        "state_of_incorporation": "Texas",
        "address": "6500 Environmental Way",
        "city": "Houston",
        "state": "TX",
        "zip": "77001",
        "phone": "(713) 555-0889",
        "sic_code": "4953",
        "sic_description": "Refuse Systems",
        "years_in_business": 12,
        "date_established": "2014-03-01",
        "nature_of_business": "Industrial waste management, environmental remediation, and hazardous waste disposal services",
        "annual_revenue": 18000000,
        "total_employees": 75,
        "total_payroll": 4500000,
        "lob": "GL",
        "manufacturing_operations": false,
        "hazmat_handling": true,
        "going_concern": true,
        "effective_date": "2026-07-01",
        "expiration_date": "2027-07-01",
        "limits_requested": 2000000,
        "retention_requested": 25000,
        "prior_carrier": "None",
        "prior_premium": 0,
        "non_renewed_by_carrier": true,
        "loss_history": [
            {"year": 2023, "claims": 2, "incurred": 95000, "paid": 80000, "reserves": 15000},
            {"year": 2024, "claims": 3, "incurred": 180000, "paid": 120000, "reserves": 60000},
            {"year": 2025, "claims": 3, "incurred": 250000, "paid": 100000, "reserves": 150000, "status": "Open"}
        ],
        "claim_details": [
            {"number": "CLM-2024-002", "date_of_loss": "2024-06-10", "claimant": "Property Owner", "type": "Environmental", "description": "Contamination of residential well water near disposal site. State environmental agency investigating.", "status": "Open", "paid": 50000, "reserves": 60000},
            {"number": "CLM-2025-003", "date_of_loss": "2025-09-01", "claimant": "Multiple Residents", "type": "Bodily Injury", "description": "Class action by residents alleging health effects from airborne contaminants. Early stage litigation.", "status": "Open", "paid": 0, "reserves": 150000}
        ],
        "loss_notes": "Prior carrier (CNA) non-renewed the policy effective 12/31/2025 citing deteriorating loss experience and pending environmental litigation.",
        "financial_data": {
            "current_year": 2025, "prior_year": 2024,
            "current_revenue": 18000000, "prior_revenue": 20000000,
            "current_net_income": -2800000, "prior_net_income": -1500000,
            "current_total_assets": 8000000, "prior_total_assets": 11000000,
            "current_total_liabilities": 7500000, "prior_total_liabilities": 6000000,
            "current_equity": 500000, "prior_equity": 5000000,
            "auditor_name": "Weaver and Tidwell LLP",
            "auditor_opinion": "Going Concern",
            "going_concern_note": "The Company has suffered significant losses, has pending environmental litigation, and was non-renewed by its prior liability carrier. These conditions raise substantial doubt about the Company's ability to continue as a going concern."
        },
        "documents_to_generate": ["gl_application", "loss_run", "financial_statement"],
        "ground_truth": {
            "classification": "gl_application",
            "risk_score": "Red",
            "routing": "refer_to_management",
            "appetite": "outside_appetite",
            "appetite_key_citations": ["§4.3 Going concern qualification", "§6.1 8 claims in 3 years exceeds maximum 5", "§6.2 Claims frequency trending UPWARD (2, 3, 3)", "Prior carrier non-renewed - severe negative signal"],
            "extracted_fields": {"named_insured": "Clearwater Environmental Services LLC", "annual_revenue": 18000000, "sic_code": "4953"}
        },
        "data_quality_notes": ["Claims trending upward (2, 3, 3) tests §6.2 trending requirement", "Non-renewed by prior carrier is a severe adverse signal", "Class action environmental litigation is high-severity"]
    },
    {
        "company_id": "redwood_timber",
        "named_insured": "Redwood Timber Products LLC",
        "fein": "10-2345678",
        "entity_type": "LLC",
        "state_of_incorporation": "Oregon",
        "address": "800 Timber Road",
        "city": "Eugene",
        "state": "OR",
        "zip": "97401",
        "phone": "(541) 555-0990",
        "sic_code": "2421",
        "sic_description": "Sawmills and Planing Mills-General",
        "years_in_business": 35,
        "date_established": "1991-06-01",
        "nature_of_business": "Lumber processing - sawmill operations producing dimensional lumber, timbers, and specialty wood products",
        "annual_revenue": 42000000,
        "annual_revenue_display": "$40-45M",
        "total_employees": 200,
        "total_payroll": 12000000,
        "lob": "GL",
        "manufacturing_operations": true,
        "products_liability_exposure": "Dimensional lumber and engineered wood products for construction. Grade-stamped per WWPA standards.",
        "hazmat_handling": false,
        "effective_date": "2026-07-01",
        "expiration_date": "2027-07-01",
        "limits_requested": 5000000,
        "retention_requested": 25000,
        "prior_carrier": "Employers Mutual",
        "prior_premium": 38000,
        "loss_history": [
            {"year": 2023, "claims": 2, "incurred": 65000, "paid": 55000, "reserves": 10000},
            {"year": 2024, "claims": 2, "incurred": 85000, "paid": 70000, "reserves": 15000},
            {"year": 2025, "claims": 2, "incurred": 110000, "paid": 60000, "reserves": 50000, "status": "Open"}
        ],
        "claim_details": [
            {"number": "CLM-2023-001", "date_of_loss": "2023-03-20", "claimant": "Employee", "type": "Bodily Injury", "description": "Saw blade laceration during lumber processing. Required surgery.", "status": "Closed", "paid": 45000, "reserves": 0},
            {"number": "CLM-2025-002", "date_of_loss": "2025-07-12", "claimant": "Contractor", "type": "Property Damage", "description": "Lumber stack collapsed during loading, damaging contractor's flatbed truck and injuring loader operator.", "status": "Open", "paid": 30000, "reserves": 50000}
        ],
        "documents_to_generate": ["gl_application", "loss_run", "supplemental_gl"],
        "ground_truth": {
            "classification": "gl_application",
            "risk_score": "Amber",
            "routing": "assign_to_senior_uw",
            "appetite": "borderline",
            "appetite_key_citations": ["§6.1 6 claims in 3 years EXCEEDS maximum 5", "§5.3 Products liability documented", "Revenue ambiguous on form - stated as range"],
            "extracted_fields": {"named_insured": "Redwood Timber Products LLC", "annual_revenue": null, "sic_code": "2421"}
        },
        "data_quality_notes": ["INTENTIONAL: Revenue stated as range '$40-45M' instead of exact number - tests extraction of ambiguous numeric values", "6 claims in 3 years is above the §6.1 maximum of 5, but not drastically so - borderline"]
    }
]
